netbox_capirca_plugin/__init__.py
netbox_capirca_plugin/admin.py
netbox_capirca_plugin/exceptions.py
netbox_capirca_plugin/filters.py
netbox_capirca_plugin/forms.py
netbox_capirca_plugin/models.py
netbox_capirca_plugin/navigation.py
netbox_capirca_plugin/tables.py
netbox_capirca_plugin/template_content.py
netbox_capirca_plugin/urls.py
netbox_capirca_plugin/utils.py
netbox_capirca_plugin/validators.py
netbox_capirca_plugin/views.py
netbox_capirca_plugin/api/__init__.py
netbox_capirca_plugin/api/serializers.py
netbox_capirca_plugin/api/urls.py
netbox_capirca_plugin/api/views.py
netbox_capirca_plugin/migrations/0001_initial.py
netbox_capirca_plugin/migrations/0002_auto_20210401_1043.py
netbox_capirca_plugin/migrations/0003_auto_20210401_1048.py
netbox_capirca_plugin/migrations/0004_auto_20210401_1202.py
netbox_capirca_plugin/migrations/0005_auto_20210401_2214.py
netbox_capirca_plugin/migrations/0006_auto_20210402_0827.py
netbox_capirca_plugin/migrations/0007_aclinterfaceassignment.py
netbox_capirca_plugin/migrations/0008_auto_20210403_0934.py
netbox_capirca_plugin/migrations/0009_auto_20210404_0804.py
netbox_capirca_plugin/migrations/0010_auto_20210404_1040.py
netbox_capirca_plugin/migrations/0011_auto_20210517_1419.py
netbox_capirca_plugin/migrations/__init__.py
netbox_capirca_plugin/templates/netbox_capirca_plugin/acl.html
netbox_capirca_plugin/templates/netbox_capirca_plugin/acl_delete.html
netbox_capirca_plugin/templates/netbox_capirca_plugin/acl_edit.html
netbox_capirca_plugin/templates/netbox_capirca_plugin/acl_interface_assignment_edit.html
netbox_capirca_plugin/templates/netbox_capirca_plugin/acl_list.html
netbox_capirca_plugin/templates/netbox_capirca_plugin/acl_render.html
netbox_capirca_plugin/templates/netbox_capirca_plugin/acl_render_response.html
netbox_capirca_plugin/templates/netbox_capirca_plugin/interface_acl.html
netbox_capirca_plugin-2.0.0.dist-info/LICENSE.txt
netbox_capirca_plugin-2.0.0.dist-info/METADATA
netbox_capirca_plugin-2.0.0.dist-info/WHEEL
netbox_capirca_plugin-2.0.0.dist-info/top_level.txt
netbox_capirca_plugin-2.0.0.dist-info/RECORD
