Metadata-Version: 2.1
Name: netbox-capirca-plugin
Version: 2.0.0
Summary: A netbox plugin to manage ACLs with capirca
Home-page: https://github.com/991jo/netbox_capirca_plugin
Author: Johannes Erwerle
Author-email: jo@swagsapce.org
License: UNKNOWN
Platform: UNKNOWN
License-File: LICENSE.txt
Requires-Dist: capirca
Requires-Dist: jinja2
Requires-Dist: netbox-plugin-extensions (>=1.1.0)
Requires-Dist: importlib
